felix_django/__init__.py
felix_django/management/__init__.py
felix_django/management/commands/__init__.py
felix_django/management/commands/dev_admin_user.py
felix_django/management/commands/wait_for_db.py
felix_django-1.0.1.dist-info/WHEEL
felix_django-1.0.1.dist-info/METADATA
felix_django-1.0.1.dist-info/RECORD
