Metadata-Version: 2.3
Name: felix-django
Version: 1.0.1
Summary: Felix' Django stuff
Author: Felix Hummel
Author-email: Felix Hummel <felix@felixhummel.de>
Requires-Dist: django
Requires-Dist: structlog
Requires-Python: >=3.11
Project-URL: Repository, https://gitlab.com/felixhummel/felix-django/
